directorywatcher.py
directorywatcher-0.1.1.dist-info/DESCRIPTION.rst
directorywatcher-0.1.1.dist-info/METADATA
directorywatcher-0.1.1.dist-info/RECORD
directorywatcher-0.1.1.dist-info/WHEEL
directorywatcher-0.1.1.dist-info/metadata.json
directorywatcher-0.1.1.dist-info/top_level.txt
